{
    "ddr4": [
        "ddr4gskill|G.Skill",
        "ddr4kingston|Kingston",
        "ddr4corsair|Corsair",
        "ddr4crucial|Crucial"
    ],
    "ddr5": [
        "ddr5gskill|G.Skill",
        "ddr5kingston|Kingston",
        "ddr5corsair|Corsair"
    ],
    "ddr4gskill": [
        "8gbddr4gskill|8 GB",
        "16gbddr4gskill|16 GB",
        "32gbddr4gskill|32 GB"
    ],
    "ddr4kingston": [
        "8gbddr4kingston|8 GB",
        "16gbddr4kingston|16 GB",
        "32gbddr4kingston|32 GB"
    ],
    "ddr4corsair": [
        "8gbddr4corsair|8 GB",
        "16gbddr4corsair|16 GB",
        "32gbddr4corsair|32 GB"
    ],
    "ddr4crucial": [
        "8gbddr4crucial|8 GB",
        "16gbddr4crucial|16 GB",
        "32gbddr4crucial|32 GB"
    ],
    "ddr5gskill": [
        "16gbddr5gskill|16 GB",
        "32gbddr5gskill|32 GB"
    ],
    "ddr5kingston": [
        "8gbddr5kingston|8 GB",
        "16gbddr5kingston|16 GB",
        "32gbddr5kingston|32 GB"
    ],
    "ddr5corsair": [
        "8gbddr5corsair|8 GB",
        "16gbddr5corsair|16 GB"
    ],
    "8gbddr4gskill|8 GB": [
        "G.Skill Ripjaws DDR4-2400 8 GB CL 16",
        "G.Skill Ripjaws V DDR4-2400 8 GB CL 17",
        "G.Skill Ripjaws DDR4-2666 8 GB CL 18",
        "G.Skill Ripjaws V DDR4-2666 8 GB CL 19",
        "G.Skill Trident Z RGB DDR4-3000 8 GB CL 16",
        "G.Skill Ripjaws DDR4-3000 8 GB CL 16",
        "G.Skill Ripjaws V DDR4-3000 8 GB CL 16",
        "G.Skill Ripjaws DDR4-3200 8 GB CL 18",
        "G.Skill Ripjaws V DDR4-3600 8 GB CL 19",
        "G.Skill Sniper X DDR4-3600 8 GB CL 19",
        "G.Skill Trident Z Royal DDR4-4000 8 GB CL 15",
        "G.Skill Trident Z Royal Elite DDR4-4000 8 GB CL 14",
        "G.Skill Trident Z Royal Elite DDR4-4600 8 GB CL 20",
        "G.Skill Trident Z RGB DDR4-4600 8 GB CL 19",
        "G.Skill Ripjaws V DDR4-4600 8 GB CL 19",
        "G.Skill Trident Z Royal DDR4-4600 8 GB CL 19"
    ],
    "16gbddr4gskill|16 GB": [
        "G.Skill Ripjaws DDR4-2400 16 GB CL 16",
        "G.Skill Ripjaws DDR4-2666 16 GB CL 18",
        "G.Skill Ripjaws V DDR4-3000 16 GB CL 16",
        "G.Skill Ripjaws V DDR4-3000 16 GB CL 15",
        "G.Skill Ripjaws V DDR4-3200 16 GB CL 16",
        "G.Skill Ripjaws DDR4-3200 16 GB CL 18",
        "G.Skill Ripjaws V DDR4-3600 16 GB CL 19",
        "G.Skill Sniper X DDR4-3600 16 GB CL 19",
        "G.Skill Trident Z Royal DDR4-4000 16 GB CL 18",
        "G.Skill Trident Z Royal Elite DDR4-4000 16 GB CL 16",
        "G.Skill Trident Z RGB DDR4-4600 16 GB CL 20",
        "G.Skill Ripjaws V DDR4-4600 16 GB CL 19",
        "G.Skill Trident Z Royal DDR4-4600 16 GB CL 20"
    ],
    "32gbddr4gskill|32 GB": [
        "G.Skill Ripjaws V DDR4-2666 32 GB CL 19",
        "G.Skill Ripjaws V DDR4-3200 32 GB CL 16",
        "G.Skill Trident Z Royal DDR4-4000 32 GB CL 18",
        "G.Skill Trident Z Royal Elite DDR4-4000 32 GB CL 18",
        "G.Skill Trident Z RGB DDR4-4600 32 GB CL 20",
        "G.Skill Ripjaws V DDR4-4600 32 GB CL 20",
        "G.Skill Trident Z RGB DDR4-4600 32 GB CL 20"
    ],
    "8gbddr4kingston|8 GB": [
        "Kingston HyperX Fury DDR4-2400 8 GB (1x8) CL 15",
        "Kingston HyperX Savage DDR4-2400 8 GB (1x8) CL 12",
        "Kingston HyperX Fury DDR4-2666 8 GB (1x8) CL 16",
        "Kingston FURY Beast DDR4-2666 8 GB (1x8) CL 16",
        "Kingston FURY Renegae DDR4-2666 8 GB (1x8) CL 13",
        "Kingston HyperX Fury DDR4-3000 8 GB (1x8) CL 15",
        "Kingston FURY Beast DDR4-3000 8 GB (1x8) CL 15",
        "Kingston HyperX Predator RGB DDR4-3000 8 GB (1x8) CL 15",
        "Kingston Savage DDR4-3000 8 GB (1x8) CL 15",
        "Kingston HyperX Savage DDR4-3000 8 GB (1x8) CL 15",
        "Kingston FURY Beast DDR4-3200 8 GB (1x8) CL 16",
        "Kingston FURY Beast RGB DDR4-3200 8 GB (1x8) CL 16",
        "Kingston HyperX Fury DDR4-3200 8 GB (1x8) CL 18",
        "Kingston HyperX Fury DDR4-3200 8 GB (1x8) CL 18",
        "Kingston HyperX Fury RGB DDR4-3200 8 GB (1x8) CL 16",
        "Kingston HyperX Predator RGB DDR4-3200 8 GB (1x8) CL 16",
        "Kingston FURY Renegade DDR4-3200 8 GB (1x8) CL 16",
        "Kingston FURY Renegade RGB DDR4-3200 8 GB (1x8) CL 16",
        "Kingston FURY Beast DDR4-3600 8 GB (1x8) CL 17",
        "Kingston FURY Renegade DDR4-3600 8 GB (1x8) CL 16",
        "Kingston FURY Renegade RGB DDR4-3600 8 GB (1x8) CL 16",
        "Kingston HyperX Predator RGB DDR4-3600 8 GB (1x8) CL 17",
        "Kingston FURY Renegade DDR4-4000 8 GB (1x8) CL 19",
        "Kingston FURY Renegade RGB DDR4-4000 8 GB (1x8) CL 19",
        "Kingston HyperX Predator RGB DDR4-4000 8 GB (1x8) CL 19",
        "Kingston FURY Beast DDR4-4800 8 GB (1x8) CL 38",
        "Kingston FURY Beast RGB DDR4-4800 8 GB (1x8) CL 38"
    ],
    "16gbddr4kingston|16 GB": [
        "Kingston HyperX Fury DDR4-2400 16 GB (1x16) CL 15",
        "Kingston HyperX Fury DDR4-2666 16 GB (1x16) CL 16",
        "Kingston HyperX Predator DDR4-2666 16 GB (1x16) CL 13",
        "Kingston FURY Beast DDR4-2666 16 GB (1x16) CL 16",
        "Kingston FURY Renegae DDR4-2666 16 GB (1x16) CL 13",
        "Kingston HyperX Predator DDR4-3000 16 GB (1x16) CL 15",
        "Kingston HyperX Fury RGB DDR4-3000 16 GB (1x16) CL 15",
        "Kingston HyperX Fury DDR4-3000 16 GB (1x16) CL 15",
        "Kingston HyperX Predator RGB DDR4-3000 16 GB (1x16) CL 15",
        "Kingston FURY Beast DDR4-3200 16 GB (1x16) CL 16",
        "Kingston FURY Beast RGB DDR4-3200 16 GB (1x16) CL 16",
        "Kingston HyperX Fury DDR4-3200 16 GB (1x16) CL 16",
        "Kingston HyperX Fury RGB DDR4-3200 16 GB (1x16) CL 16",
        "Kingston HyperX Predator RGB DDR4-3200 16 GB (1x16) CL 16",
        "Kingston HyperX Predator DDR4-3200 16 GB (1x16) CL 16",
        "Kingston FURY Renegade DDR4-3200 16 GB (1x16) CL 16",
        "Kingston FURY Renegade RGB DDR4-3200 16 GB (1x16) CL 16",
        "Kingston FURY Beast DDR4-3600 16 GB (1x16) CL 18",
        "Kingston FURY Renegade DDR4-3600 16 GB (1x16) CL 16",
        "Kingston FURY Renegade RGB DDR4-3600 16 GB (1x16) CL 16",
        "Kingston FURY Renegade DDR4-4000 16 GB (1x16) CL 19",
        "Kingston FURY Beast DDR4-4800 16 GB (1x16) CL 38",
        "Kingston FURY Beast RGB DDR4-4800 16 GB (1x16) CL 38"
    ],
    "32gbddr4kingston|32 GB": [
        "Kingston FURY Beast DDR4-2666 32 GB (1x32) CL 16",
        "Kingston FURY Renegae DDR4-2666 32 GB (1x32) CL 15",
        "Kingston FURY Beast DDR4-3200 32 GB (1x32) CL 16",
        "Kingston HyperX Fury DDR4-3200 32 GB (1x32) CL 16",
        "Kingston FURY Renegade DDR4-3200 32 GB (1x32) CL 16",
        "Kingston FURY Renegade RGB DDR4-3200 32 GB (1x32) CL 16",
        "Kingston FURY Beast DDR4-3600 32 GB (1x32) CL 17",
        "Kingston FURY Renegade DDR4-3600 32 GB (1x32) CL 18",
        "Kingston FURY Renegade RGB DDR4-3600 32 GB (1x32) CL 18",
        "Kingston FURY Beast DDR4-4800 32 GB (1x32) CL 38",
        "Kingston FURY Beast RGB DDR4-4800 32 GB (1x32) CL 38"
    ],
    "8gbddr4corsair|8 GB": [
        "Corsair Vengeance LPX DDR4-2400 8 GB (1x8) CL 16",
        "Corsair Vengeance LPX DDR4-2666 8 GB (1x8) CL 16",
        "Corsair Vengeance RGB PRO DDR4-2666 8 GB (1x16) CL 16",
        "Corsair Vengeance LPX DDR4-3000 8 GB (1x8) CL 16",
        "Corsair Vengeance LED DDR4-3000 8 GB (1x8) CL 16",
        "Corsair Vengeance LPX DDR4-3200 8 GB (1x8) CL 16",
        "Corsair Vengeance RGB PRO DDR4-3200 8 GB (1x8) CL 16",
        "Corsair Vengeance LPX DDR4-3600 8 GB (1x8) CL 18",
        "Corsair Vengeance RGB Pro DDR4-4000 8 GB (1x8) CL 18",
        "Corsair Dominator Platinum DDR4-4000 8 GB (1x8) CL 19",
        "Corsair Vengeance RGB Pro DDR4-4700 8 GB (1x8) CL 19",
        "Corsair Dominator Platinum DDR4-4800 8 GB (1x8) CL 19",
        "Corsair Vengeance LPX DDR4-4800 8 GB (1x8) CL 19"
    ],
    "16gbddr4corsair|16 GB": [
        "Corsair Vengeance LPX DDR4-2400 16 GB (1x16) CL 16",
        "Corsair Vengeance LPX DDR4-2666 16 GB (1x16) CL 16",
        "Corsair Vengeance RGB PRO DDR4-2666 16 GB (1x16) CL 16",
        "Corsair Vengeance LPX DDR4-3000 16 GB (1x16) CL 16",
        "Corsair Vengeance LED DDR4-3000 16 GB (1x16) CL 16",
        "Corsair Vengeance LPX DDR4-3200 16 GB (1x16) CL 16",
        "Corsair Vengeance RGB PRO DDR4-3200 16 GB (1x16) CL 16",
        "Corsair Vengeance LPX DDR4-3600 16 GB (1x16) CL 18",
        "Corsair Vengeance RGB PRO DDR4-3600 16 GB (1x16) CL 18",
        "Corsair Vengeance LPX DDR4-4000 16 GB (1x16) CL 18",
        "Corsair Vengeance RGB Pro DDR4-4000 16 GB (1x16) CL 18",
        "Corsair Dominator Platinum DDR4-4000 16 GB (1x16) CL 19",
        "Corsair Vengeance LPX DDR4-4600 16 GB (1x8) CL 19",
        "Corsair Vengeance RGB DDR4-4600 16 GB (1x16) CL 19"
    ],
    "32gbddr4corsair|32 GB": [
        "Corsair Vengeance LPX DDR4-2400 32 GB (1x32) CL 16",
        "Corsair Vengeance LPX DDR4-2666 32 GB (1x32) CL 16",
        "Corsair Vengeance RGB PRO DDR4-2666 32 GB (1x8) CL 16",
        "Corsair Vengeance LPX DDR4-3000 32 GB (1x32) CL 16",
        "Corsair Vengeance LED DDR4-3000 32 GB (1x32) CL 16",
        "Corsair Vengeance LPX DDR4-4000 32 GB (1x32) CL 18",
        "Corsair Vengeance RGB Pro DDR4-4000 32 GB (1x32) CL 18"
    ],
    "8gbddr4crucial|8 GB": [
        "Crucial Ballistix Sport LT DDR4-2400 8 GB CL 16",
        "Crucial Ballistix DDR4-2400 8 GB CL 16",
        "Crucial Ballistix Sport AT DDR4-2666 8 GB CL 16",
        "Crucial Ballistix Sport LT DDR4-2666 8 GB CL 16",
        "Crucial Ballistix Tactical Tracer DDR4-3200 8 GB CL 16",
        "Crucial Ballistix Sport LT DDR4-3200 8 GB CL 16",
        "Crucial Ballistix Elite DDR4-3600 8 GB CL 16",
        "Crucial Ballistix Max RGB DDR4-4000 8 GB CL 18",
        "Crucial Ballistix Elite DDR4-4000 8 GB CL 18",
        "Crucial Ballistix MAX DDR4-4400 8 GB CL 19"
    ],
    "16gbddr4crucial|16 GB": [
        "Crucial Ballistix Sport LT DDR4-2400 16 GB CL 16",
        "Crucial Ballistix Sport AT DDR4-2666 16 GB CL 16",
        "Crucial Ballistix Sport LT DDR4-2666 16 GB CL 16",
        "Crucial Ballistix Tactical Tracer DDR4-2666 16 GB CL 16",
        "Crucial Ballistix DDR4-2666 16 GB CL 16",
        "Crucial Ballistix Sport AT DDR4-3000 16 GB CL 17",
        "Crucial Ballistix Sport LT DDR4-3000 16 GB CL 15",
        "Crucial Ballistix Elite DDR4-3000 16 GB CL 15",
        "Crucial Ballistix Tactical DDR4-3000 16 GB CL 15",
        "Crucial Ballistix Tactical Tracer DDR4-3000 16 GB CL 16",
        "Crucial Ballistix Elite DDR4-3200 16 GB CL 16",
        "Crucial Ballistix Sport LT DDR4-3200 16 GB CL 16",
        "Crucial Ballistix RGB DDR4-3200 16 GB CL 16",
        "Crucial Ballistix Sport LT DDR4-3200 16 GB CL 16",
        "Crucial Ballistix DDR4-3600 16 GB CL 16",
        "Crucial Ballistix Max RGB DDR4-4000 16 GB CL 18",
        "Crucial Ballistix MAX DDR4-4400 16 GB CL 19"
    ],
    "32gbddr4crucial|32 GB": [
        "Crucial Ballistix DDR4-3600 32 GB CL 16",
        "Crucial Ballistix RGB DDR4-3600 32 GB CL 16"
    ],
    "16gbddr5gskill|16 GB": [
        "ripjaws16|Ripjaws S5 DDR5-5200 16 GB CL 28",
        "trident16|Trident Z5 RGB DDR5-5600 16 GB CL 40",
        "ripjaws16|Ripjaws S5 DDR5-6000 16 GB CL 40",
        "trident16|Trident Z5 RGB DDR5-6000 16 GB CL 32",
        "trident16|Trident Z DDR5-6400 16 GB CL 32",
        "trident16|Trident Z5 RGB DDR5-6400 16 GB CL 32",
        "trident16|Trident Z5 RGB DDR5-6600 16 GB CL 32"
    ],
    "32gbddr5gskill|32 GB": [
        "ripjaws32|Ripjaws S5 DDR5-5200 32 GB CL 28",
        "ripjaws32|Ripjaws S5 DDR5-5600 32 GB CL 28",
        "trident32|Trident Z5 RGB DDR5-6000 32 GB CL 32"
    ],
    "8gbddr5kingston": [
        "fury8|Kingston FURY Beast DDR5-5200 8 GB CL 40",
        "fury8|Kingston FURY Beast RGB DDR5-5200 8 GB CL 40",
        "fury8|Kingston FURY Beast DDR5-5600 8 GB CL 40",
        "fury8|Kingston FURY Beast RGB DDR5-5600 8 GB CL 40",
        "fury8|Kingston FURY Beast DDR5-6000 8 GB CL 40",
        "fury8|Kingston FURY Beast RGB DDR5-6000 8 GB CL 40"
    ],
    "16gbddr5kingston": [
        "fury16|Kingston FURY Beast DDR5-5200 16 GB CL 40",
        "fury16|Kingston FURY Beast RGB DDR5-5200 16 GB CL 40"
    ],
    "32gbddr5kingston": [
        "fury32|Kingston FURY Beast RGB DDR5-5200 32 GB CL 40",
        "fury32|Kingston FURY Beast DDR5-5600 32 GB CL 40",
        "fury32|Kingston FURY Beast RGB DDR5-5600 32 GB CL 40"
    ],
    "8gbddr5corsair": [
        "Corsair Vengeance RGB DDR5-6600 8 GB CL 32"
    ],
    "16gbddr5corsair": [
        "Corsair Vengeance RGB DDR5-6600 16 GB CL 32",
        "Corsair Dominator Platinum RGB DDR5-6600 16 GB CL 32",
        "Corsair Dominator Platinum RGB DDR5-6400 16 GB CL 38",
        "Corsair Vengeance RGB DDR5-6400 16 GB CL 38",
        "Corsair Dominator Platinum RGB DDR5-6200 16 GB CL 36",
        "Corsair Vengeance RGB DDR5-6200 16 GB CL 36",
        "Corsair Vengeance DDR5-6200 16 GB CL 36",
        "Corsair Vengeance DDR5-6000 16 GB CL 36",
        "Corsair Dominator Platinum RGB DDR5-6000 16 GB CL 36",
        "Corsair Vengeance RGB DDR5-6000 16 GB CL 40",
        "Corsair Vengeance RGB DDR5-6000 16 GB CL 36",
        "Corsair Vengeance DDR5-6000 16 GB CL 40"
    ]
}